starlette_discord/__init__.py
starlette_discord/client.py
starlette_discord/models.py
starlette_discord/oauth.py
starlette_discord-0.2.1.dist-info/LICENSE
starlette_discord-0.2.1.dist-info/METADATA
starlette_discord-0.2.1.dist-info/WHEEL
starlette_discord-0.2.1.dist-info/top_level.txt
starlette_discord-0.2.1.dist-info/RECORD
