Metadata-Version: 2.1
Name: starlette-discord
Version: 0.2.1
Summary: "Login with Discord" support for Starlette and FastAPI.
Home-page: https://github.com/nwunderly/starlette-discord
Author: nwunderly
Project-URL: Documentation, https://starlette-discord.rtfd.io/
Classifier: Development Status :: 2 - Pre-Alpha
Classifier: License :: OSI Approved :: MIT License
Classifier: Intended Audience :: Developers
Classifier: Natural Language :: English
Classifier: Operating System :: OS Independent
Classifier: Programming Language :: Python :: 3.8
Classifier: Topic :: Internet
Classifier: Topic :: Software Development :: Libraries
Classifier: Topic :: Software Development :: Libraries :: Python Modules
Classifier: Topic :: Utilities
Requires-Python: >=3.8
License-File: LICENSE
Requires-Dist: discord.py (<2,>=1.7)
Requires-Dist: oauthlib
Requires-Dist: starlette (>=0.13.6)
Provides-Extra: docs
Requires-Dist: sphinx ; extra == 'docs'
Requires-Dist: sphinxcontrib-trio ; extra == 'docs'
Requires-Dist: myst-parser ; extra == 'docs'
